zcash_service_status/__init__.py
zcash_service_status/communities_and_forums_response_time.py
zcash_service_status-0.1.2.dist-info/LICENSE
zcash_service_status-0.1.2.dist-info/METADATA
zcash_service_status-0.1.2.dist-info/WHEEL
zcash_service_status-0.1.2.dist-info/top_level.txt
zcash_service_status-0.1.2.dist-info/RECORD
